<?xml version="1.0" encoding="UTF-8" standalone="yes"?>
<RSLogix5000Content SchemaRevision="1.0" SoftwareRevision="33.00" TargetName="_Phase_Autofill" TargetType="Routine" TargetSubType="RLL" TargetClass="Standard" ContainsContext="true" ExportDate="Fri Jan 27 15:01:41 2023" ExportOptions="References NoRawData L5KData DecoratedData Context Dependencies ForceProtectedEncoding AllProjDocTrans">
	<Controller Use="Context" Name="BatterDepositor">
		<DataTypes Use="Context">
			<DataType Name="Cmd_Action" Family="NoFamily" Class="User">
				<Members>
					<Member Name="ZZZZZZZZZZCmd_Action0" DataType="SINT" Dimension="0" Radix="Decimal" Hidden="true" ExternalAccess="Read/Write"/>
					<Member Name="Request" DataType="BIT" Dimension="0" Radix="Decimal" Hidden="false" Target="ZZZZZZZZZZCmd_Action0" BitNumber="0" ExternalAccess="Read/Write">
						<Description>
							<![CDATA[Requests action]]>
						</Description>
					</Member>
					<Member Name="Feedback" DataType="BIT" Dimension="0" Radix="Decimal" Hidden="false" Target="ZZZZZZZZZZCmd_Action0" BitNumber="1" ExternalAccess="Read/Write">
						<Description>
							<![CDATA[Handshake]]>
						</Description>
					</Member>
				</Members>
			</DataType>
		</DataTypes>
		<AddOnInstructionDefinitions Use="Context">
			<AddOnInstructionDefinition Name="Function" Class="Standard" Revision="1.0" ExecutePrescan="false" ExecutePostscan="false" ExecuteEnableInFalse="true" CreatedDate="2023-01-25T10:29:54.757Z" CreatedBy="WPI\tom.reit" EditedDate="2023-01-27T08:55:42.996Z" EditedBy="WPI\tom.reit" SoftwareRevision="v33.00"
>
				<Parameters>
					<Parameter Name="EnableIn" TagType="Base" DataType="BOOL" Usage="Input" Radix="Decimal" Required="false" Visible="false" ExternalAccess="Read Only">
						<Description>
							<![CDATA[Enable Input - System Defined Parameter]]>
						</Description>
					</Parameter>
					<Parameter Name="EnableOut" TagType="Base" DataType="BOOL" Usage="Output" Radix="Decimal" Required="false" Visible="false" ExternalAccess="Read Only">
						<Description>
							<![CDATA[Enable Output - System Defined Parameter]]>
						</Description>
					</Parameter>
					<Parameter Name="Enabled" TagType="Base" DataType="BOOL" Usage="Output" Radix="Decimal" Required="false" Visible="true" ExternalAccess="Read/Write">
						<Description>
							<![CDATA[Function is enabled]]>
						</Description>
						<DefaultData Format="L5K">
							<![CDATA[0]]>
						</DefaultData>
						<DefaultData Format="Decorated">
							<DataValue DataType="BOOL" Radix="Decimal" Value="0"/>
						</DefaultData>
					</Parameter>
					<Parameter Name="Active" TagType="Base" DataType="BOOL" Usage="Output" Radix="Decimal" Required="false" Visible="true" ExternalAccess="Read/Write">
						<Description>
							<![CDATA[Function is active]]>
						</Description>
						<DefaultData Format="L5K">
							<![CDATA[0]]>
						</DefaultData>
						<DefaultData Format="Decorated">
							<DataValue DataType="BOOL" Radix="Decimal" Value="0"/>
						</DefaultData>
					</Parameter>
					<Parameter Name="Command" TagType="Base" DataType="Cmd_Action" Usage="InOut" Required="true" Visible="true" Constant="false"/>
					<Parameter Name="Warning" TagType="Base" DataType="BOOL" Usage="Output" Radix="Decimal" Required="false" Visible="true" ExternalAccess="Read/Write">
						<Description>
							<![CDATA[Feedback was not active within a second. ]]>
						</Description>
						<DefaultData Format="L5K">
							<![CDATA[0]]>
						</DefaultData>
						<DefaultData Format="Decorated">
							<DataValue DataType="BOOL" Radix="Decimal" Value="0"/>
						</DefaultData>
					</Parameter>
				</Parameters>
				<LocalTags>
					<LocalTag Name="T_feedbackCheck" DataType="TIMER" ExternalAccess="None">
						<DefaultData Format="L5K">
							<![CDATA[[0,1000,0]]]>
						</DefaultData>
						<DefaultData Format="Decorated">
							<Structure DataType="TIMER">
								<DataValueMember Name="PRE" DataType="DINT" Radix="Decimal" Value="1000"/>
								<DataValueMember Name="ACC" DataType="DINT" Radix="Decimal" Value="0"/>
								<DataValueMember Name="EN" DataType="BOOL" Value="0"/>
								<DataValueMember Name="TT" DataType="BOOL" Value="0"/>
								<DataValueMember Name="DN" DataType="BOOL" Value="0"/>
							</Structure>
						</DefaultData>
					</LocalTag>
				</LocalTags>
				<Routines>
					<Routine Name="EnableInFalse" Type="ST">
						<STContent>
							<Line Number="0">
								<![CDATA[////////////////////////////////////////////////////////////]]>
							</Line>
							<Line Number="1">
								<![CDATA[//   Copyright (c)  ]]>
							</Line>
							<Line Number="2">
								<![CDATA[//------------------------------------------------------------]]>
							</Line>
							<Line Number="3">
								<![CDATA[//   Routine: EnableInFalse]]>
							</Line>
							<Line Number="4">
								<![CDATA[//   Author: WPI\tom.reit]]>
							</Line>
							<Line Number="5">
								<![CDATA[//   Created: 25-1-2023]]>
							</Line>
							<Line Number="6">
								<![CDATA[//------------------------------------------------------------]]>
							</Line>
							<Line Number="7">
								<![CDATA[//   Description:]]>
							</Line>
							<Line Number="8">
								<![CDATA[//           ]]>
							</Line>
							<Line Number="9">
								<![CDATA[//]]>
							</Line>
							<Line Number="10">
								<![CDATA[//   History:]]>
							</Line>
							<Line Number="11">
								<![CDATA[//]]>
							</Line>
							<Line Number="12">
								<![CDATA[////////////////////////////////////////////////////////////]]>
							</Line>
							<Line Number="13">
								<![CDATA[Enabled		:=0;]]>
							</Line>
							<Line Number="14">
								<![CDATA[Active		:=0;]]>
							</Line>
						</STContent>
					</Routine>
					<Routine Name="Logic" Type="RLL">
						<RLLContent>
							<Rung Number="0" Type="N">
								<Text>
									<![CDATA[XIC(EnableIn)OTE(Enabled);]]>
								</Text>
							</Rung>
							<Rung Number="1" Type="N">
								<Text>
									<![CDATA[XIC(Command.Request)XIC(Command.Feedback)OTE(Active);]]>
								</Text>
							</Rung>
							<Rung Number="2" Type="N">
								<Text>
									<![CDATA[XIC(Enabled)XIC(Command.Request)XIO(Command.Feedback)TON(T_feedbackCheck,?,?)XIC(T_feedbackCheck.DN)OTE(Warning);]]>
								</Text>
							</Rung>
						</RLLContent>
					</Routine>
				</Routines>
				<Dependencies>
					<Dependency Type="DataType" Name="Cmd_Action"/>
				</Dependencies>
			</AddOnInstructionDefinition>
		</AddOnInstructionDefinitions>
		<AlarmDefinitions Use="Context">
			<DatatypeAlarmDefinition Name="Function">
				<MemberAlarmDefinition Name="FunctionWarning" Input=".Warning" ConditionType="TRIP" Limit="0.0" Severity="1" OnDelay="0" OffDelay="0" ShelveDuration="0" MaxShelveDuration="0" Deadband="0.0" Required="false"
				 AlarmSetOperIncluded="true" AlarmSetRollupIncluded="true" AckRequired="true" Latched="false" EvaluationPeriod="500 millisecond" Expression="= 1">
					<AlarmConfig>
						<Messages>
							<Message Type="ADM">
								<Text Lang="en-US">
									<![CDATA[| /*S:0 %AlarmName*/ | Request is active but feedback is not active |]]>
								</Text>
							</Message>
						</Messages>
						<AlarmClass>
							<![CDATA[Functions]]>
						</AlarmClass>
					</AlarmConfig>
				</MemberAlarmDefinition>
			</DatatypeAlarmDefinition>
		</AlarmDefinitions>
		<Programs Use="Context">
			<Program Use="Context" Name="Unit4_Depositor_Obj_Model" Class="Standard">
				<Tags Use="Context">
					<Tag Name="Cmd_Autofill" TagType="Base" DataType="Cmd_Action" Usage="Public" Constant="false" ExternalAccess="Read/Write">
						<Data Format="L5K">
							<![CDATA[[0]]]>
						</Data>
						<Data Format="Decorated">
							<Structure DataType="Cmd_Action">
								<DataValueMember Name="Request" DataType="BOOL" Value="0"/>
								<DataValueMember Name="Feedback" DataType="BOOL" Value="0"/>
							</Structure>
						</Data>
					</Tag>
					<Tag Name="PH_Autofill" TagType="Base" DataType="Function" Usage="Public" Constant="false" ExternalAccess="Read/Write">
						<AlarmConditions>
							<AlarmCondition Name="FunctionWarning" AlarmConditionDefinition="FunctionWarning" Input=".Warning" ConditionType="TRIP" Limit="0.0" Severity="1" OnDelay="0" OffDelay="0" ShelveDuration="0" MaxShelveDuration="0" Deadband="0.0"
							 Used="true" AlarmSetOperIncluded="true" AlarmSetRollupIncluded="true" InFault="false" AckRequired="true" Latched="false" ProgAck="false" OperAck="false" ProgReset="false" OperReset="false" ProgSuppress="false"
							 OperSuppress="false" ProgUnsuppress="false" OperUnsuppress="false" OperShelve="false" ProgUnshelve="false" OperUnshelve="false" ProgDisable="false" OperDisable="false" ProgEnable="false" OperEnable="false" AlarmCountReset="false"
							 EvaluationPeriod="500 millisecond" Expression="= 1">
								<AlarmConfig/>
							</AlarmCondition>
						</AlarmConditions>
						<Data Format="L5K">
							<![CDATA[[5,[0,0,0]]]]>
						</Data>
						<Data Format="Decorated">
							<Structure DataType="Function">
								<DataValueMember Name="EnableIn" DataType="BOOL" Value="1"/>
								<DataValueMember Name="EnableOut" DataType="BOOL" Value="0"/>
								<DataValueMember Name="Enabled" DataType="BOOL" Value="1"/>
								<DataValueMember Name="Active" DataType="BOOL" Value="0"/>
								<DataValueMember Name="Warning" DataType="BOOL" Value="0"/>
							</Structure>
						</Data>
					</Tag>
					<Tag Name="wrk_Autofill_HighLevel" TagType="Base" DataType="REAL" Radix="Float" Constant="false" ExternalAccess="Read/Write">
						<Data Format="L5K">
							<![CDATA[2.00000000e+001]]>
						</Data>
						<Data Format="Decorated">
							<DataValue DataType="REAL" Radix="Float" Value="20.0"/>
						</Data>
					</Tag>
					<Tag Name="wrk_Autofill_lowLevel" TagType="Base" DataType="REAL" Radix="Float" Constant="false" ExternalAccess="Read/Write">
						<Data Format="L5K">
							<![CDATA[5.00000000e+000]]>
						</Data>
						<Data Format="Decorated">
							<DataValue DataType="REAL" Radix="Float" Value="5.0"/>
						</Data>
					</Tag>
				</Tags>
				<Routines Use="Context">
					<Routine Use="Target" Name="_Phase_Autofill" Type="RLL">
						<RLLContent>
							<Rung Number="0" Type="N">
								<Text>
									<![CDATA[XIC(PH_Autofill.Enabled)[GRT(?,wrk_Autofill_HighLevel) OTU(Cmd_Autofill.Request) ,LES(?,wrk_Autofill_lowLevel) OTL(Cmd_Autofill.Request) ];]]>
								</Text>
							</Rung>
							<Rung Number="1" Type="N">
								<Text>
									<![CDATA[XIO(PH_Autofill.Enabled)OTU(Cmd_Autofill.Request);]]>
								</Text>
							</Rung>
							<Rung Number="2" Type="N">
								<Text>
									<![CDATA[XIC(Cmd_Autofill.Request)XIC(?)OTE(Cmd_Autofill.Feedback);]]>
								</Text>
							</Rung>
						</RLLContent>
					</Routine>
				</Routines>
			</Program>
		</Programs>
	</Controller>
</RSLogix5000Content>
